LICENSE
MANIFEST.in
README.md
setup.cfg
setup.py
django_products.egg-info/PKG-INFO
django_products.egg-info/SOURCES.txt
django_products.egg-info/dependency_links.txt
django_products.egg-info/requires.txt
django_products.egg-info/top_level.txt
products/__init__.py
products/admin.py
products/api.py
products/apps.py
products/models.py
products/serializers.py
products/tests.py
products/urls.py
products/views.py